{"data":[{"type":"node--article","id":"bba1d804-699f-4e87-979d-9d508dffa986","attributes":{"nid":1,"uuid":"bba1d804-699f-4e87-979d-9d508dffa986","vid":2,"langcode":"en","revision_timestamp":1524445955,"revision_log":null,"status":true,"title":"Article One","created":1524445776,"changed":1524445955,"promote":true,"sticky":false,"default_langcode":true,"revision_translation_affected":true,"path":{"alias":null,"pid":null,"langcode":"en"},"body":{"value":"\u003Cp\u003EThis is a really cool article\u003C\/p\u003E\r\n","format":"basic_html","processed":"\u003Cp\u003EThis is a really cool article\u003C\/p\u003E","summary":""},"comment":{"status":2,"cid":0,"last_comment_timestamp":1524445793,"last_comment_name":null,"last_comment_uid":1,"comment_count":0}},"relationships":{"type":{"data":{"type":"node_type--node_type","id":"afb871e7-65f6-475c-8124-ad3d235f65c3"},"links":{"self":"https:\/\/s1.demo.opensourcecms.com\/drupal\/jsonapi\/node\/article\/bba1d804-699f-4e87-979d-9d508dffa986\/relationships\/type","related":"https:\/\/s1.demo.opensourcecms.com\/drupal\/jsonapi\/node\/article\/bba1d804-699f-4e87-979d-9d508dffa986\/type"}},"revision_uid":{"data":{"type":"user--user","id":"ed718b5d-1f91-4b1c-9092-cbc1c1f92d6e"},"links":{"self":"https:\/\/s1.demo.opensourcecms.com\/drupal\/jsonapi\/node\/article\/bba1d804-699f-4e87-979d-9d508dffa986\/relationships\/revision_uid","related":"https:\/\/s1.demo.opensourcecms.com\/drupal\/jsonapi\/node\/article\/bba1d804-699f-4e87-979d-9d508dffa986\/revision_uid"}},"uid":{"data":{"type":"user--user","id":"ed718b5d-1f91-4b1c-9092-cbc1c1f92d6e"},"links":{"self":"https:\/\/s1.demo.opensourcecms.com\/drupal\/jsonapi\/node\/article\/bba1d804-699f-4e87-979d-9d508dffa986\/relationships\/uid","related":"https:\/\/s1.demo.opensourcecms.com\/drupal\/jsonapi\/node\/article\/bba1d804-699f-4e87-979d-9d508dffa986\/uid"}},"field_author":{"data":[{"type":"paragraph--author","id":"d7df9f3c-f273-4190-a327-8ca9ac3d027f","meta":{"target_revision_id":"5"}}],"links":{"self":"https:\/\/s1.demo.opensourcecms.com\/drupal\/jsonapi\/node\/article\/bba1d804-699f-4e87-979d-9d508dffa986\/relationships\/field_author","related":"https:\/\/s1.demo.opensourcecms.com\/drupal\/jsonapi\/node\/article\/bba1d804-699f-4e87-979d-9d508dffa986\/field_author"}},"field_image":{"data":null,"links":{"self":"https:\/\/s1.demo.opensourcecms.com\/drupal\/jsonapi\/node\/article\/bba1d804-699f-4e87-979d-9d508dffa986\/relationships\/field_image","related":"https:\/\/s1.demo.opensourcecms.com\/drupal\/jsonapi\/node\/article\/bba1d804-699f-4e87-979d-9d508dffa986\/field_image"}},"field_tags":{"data":[],"links":{"self":"https:\/\/s1.demo.opensourcecms.com\/drupal\/jsonapi\/node\/article\/bba1d804-699f-4e87-979d-9d508dffa986\/relationships\/field_tags","related":"https:\/\/s1.demo.opensourcecms.com\/drupal\/jsonapi\/node\/article\/bba1d804-699f-4e87-979d-9d508dffa986\/field_tags"}}},"links":{"self":"https:\/\/s1.demo.opensourcecms.com\/drupal\/jsonapi\/node\/article\/bba1d804-699f-4e87-979d-9d508dffa986"}},{"type":"node--article","id":"7c834a9f-d10c-4e28-800f-9eb8c756677b","attributes":{"nid":2,"uuid":"7c834a9f-d10c-4e28-800f-9eb8c756677b","vid":3,"langcode":"en","revision_timestamp":1524446018,"revision_log":null,"status":true,"title":"Article Two","created":1524445968,"changed":1524446018,"promote":true,"sticky":false,"default_langcode":true,"revision_translation_affected":true,"path":{"alias":null,"pid":null,"langcode":"en"},"body":{"value":"\u003Cp\u003EThis is my body\u003C\/p\u003E\r\n","format":"basic_html","processed":"\u003Cp\u003EThis is my body\u003C\/p\u003E","summary":""},"comment":{"status":2,"cid":0,"last_comment_timestamp":1524446018,"last_comment_name":null,"last_comment_uid":1,"comment_count":0}},"relationships":{"type":{"data":{"type":"node_type--node_type","id":"afb871e7-65f6-475c-8124-ad3d235f65c3"},"links":{"self":"https:\/\/s1.demo.opensourcecms.com\/drupal\/jsonapi\/node\/article\/7c834a9f-d10c-4e28-800f-9eb8c756677b\/relationships\/type","related":"https:\/\/s1.demo.opensourcecms.com\/drupal\/jsonapi\/node\/article\/7c834a9f-d10c-4e28-800f-9eb8c756677b\/type"}},"revision_uid":{"data":{"type":"user--user","id":"ed718b5d-1f91-4b1c-9092-cbc1c1f92d6e"},"links":{"self":"https:\/\/s1.demo.opensourcecms.com\/drupal\/jsonapi\/node\/article\/7c834a9f-d10c-4e28-800f-9eb8c756677b\/relationships\/revision_uid","related":"https:\/\/s1.demo.opensourcecms.com\/drupal\/jsonapi\/node\/article\/7c834a9f-d10c-4e28-800f-9eb8c756677b\/revision_uid"}},"uid":{"data":{"type":"user--user","id":"ed718b5d-1f91-4b1c-9092-cbc1c1f92d6e"},"links":{"self":"https:\/\/s1.demo.opensourcecms.com\/drupal\/jsonapi\/node\/article\/7c834a9f-d10c-4e28-800f-9eb8c756677b\/relationships\/uid","related":"https:\/\/s1.demo.opensourcecms.com\/drupal\/jsonapi\/node\/article\/7c834a9f-d10c-4e28-800f-9eb8c756677b\/uid"}},"field_author":{"data":[{"type":"paragraph--author","id":"0301033f-fb49-4344-8700-122dd9acd3e5","meta":{"target_revision_id":"6"}}],"links":{"self":"https:\/\/s1.demo.opensourcecms.com\/drupal\/jsonapi\/node\/article\/7c834a9f-d10c-4e28-800f-9eb8c756677b\/relationships\/field_author","related":"https:\/\/s1.demo.opensourcecms.com\/drupal\/jsonapi\/node\/article\/7c834a9f-d10c-4e28-800f-9eb8c756677b\/field_author"}},"field_image":{"data":null,"links":{"self":"https:\/\/s1.demo.opensourcecms.com\/drupal\/jsonapi\/node\/article\/7c834a9f-d10c-4e28-800f-9eb8c756677b\/relationships\/field_image","related":"https:\/\/s1.demo.opensourcecms.com\/drupal\/jsonapi\/node\/article\/7c834a9f-d10c-4e28-800f-9eb8c756677b\/field_image"}},"field_tags":{"data":[],"links":{"self":"https:\/\/s1.demo.opensourcecms.com\/drupal\/jsonapi\/node\/article\/7c834a9f-d10c-4e28-800f-9eb8c756677b\/relationships\/field_tags","related":"https:\/\/s1.demo.opensourcecms.com\/drupal\/jsonapi\/node\/article\/7c834a9f-d10c-4e28-800f-9eb8c756677b\/field_tags"}}},"links":{"self":"https:\/\/s1.demo.opensourcecms.com\/drupal\/jsonapi\/node\/article\/7c834a9f-d10c-4e28-800f-9eb8c756677b"}}],"jsonapi":{"version":"1.0","meta":{"links":{"self":"http:\/\/jsonapi.org\/format\/1.0\/"}}},"links":{"self":"https:\/\/s1.demo.opensourcecms.com\/drupal\/jsonapi\/node\/article"}}